libname/__init__.py
libname/main.py
resnetcarvana-0.0.1.dist-info/METADATA
resnetcarvana-0.0.1.dist-info/WHEEL
resnetcarvana-0.0.1.dist-info/top_level.txt
resnetcarvana-0.0.1.dist-info/RECORD
