Metadata-Version: 2.1
Name: resnetcarvana
Version: 0.0.1
Summary: plz work
Home-page: UNKNOWN
Author: Sha
Author-email: sliu23009@gmail.com
License: UNKNOWN
Keywords: python
Platform: UNKNOWN
Classifier: Development Status :: 1 - Planning
Classifier: Intended Audience :: Developers
Classifier: Programming Language :: Python :: 3
Classifier: Operating System :: Unix
Classifier: Operating System :: MacOS :: MacOS X
Classifier: Operating System :: Microsoft :: Windows
Requires-Dist: opencv-python
